s3datakit/__init__.py
s3datakit/core.py
s3_datakit-0.3.9.dist-info/METADATA
s3_datakit-0.3.9.dist-info/WHEEL
s3_datakit-0.3.9.dist-info/top_level.txt
s3_datakit-0.3.9.dist-info/RECORD
