Metadata-Version: 2.4
Name: s3-datakit
Version: 0.3.9
Summary: A Python toolkit to simplify common operations between S3 and Pandas.
Author-email: Carlos Coelho <coelho.carlosw@gmail.com>
License: MIT License
Classifier: Programming Language :: Python :: 3
Classifier: License :: OSI Approved :: MIT License
Classifier: Operating System :: OS Independent
Classifier: Topic :: Software Development :: Libraries :: Python Modules
Classifier: Topic :: Utilities
Requires-Python: >=3.8
Requires-Dist: boto3>=1.40.6
Requires-Dist: pandas>=2.3.1
Requires-Dist: python-dotenv
Requires-Dist: tzlocal==5.3.1
